README.rst
setup.py
robophery/__init__.py
robophery/base.py
robophery/cli.py
robophery/compat.py
robophery/conf.py
robophery.egg-info/PKG-INFO
robophery.egg-info/SOURCES.txt
robophery.egg-info/dependency_links.txt
robophery.egg-info/entry_points.txt
robophery.egg-info/not-zip-safe
robophery.egg-info/top_level.txt
robophery/comm/__init__.py
robophery/comm/graphite.py
robophery/comm/mqtt.py
robophery/comm/statsd.py
robophery/comm/linux/__init__.py
robophery/comm/linux/graphite.py
robophery/comm/linux/mqtt.py
robophery/comm/linux/statsd.py
robophery/comm/nodemcu/__init__.py
robophery/comm/nodemcu/mqtt.py
robophery/interface/__init__.py
robophery/interface/ble.py
robophery/interface/gpio.py
robophery/interface/i2c.py
robophery/interface/pwm.py
robophery/interface/spi.py
robophery/interface/w1.py
robophery/module/__init__.py
robophery/module/ble/__init__.py
robophery/module/ble/cc2541.py
robophery/module/ble/pfp.py
robophery/module/gpio/__init__.py
robophery/module/gpio/dht11.py
robophery/module/gpio/dht22.py
robophery/module/gpio/hcsr04.py
robophery/module/gpio/hd44780.py
robophery/module/gpio/l293d.py
robophery/module/gpio/relay.py
robophery/module/gpio/rev_counter.py
robophery/module/gpio/switch.py
robophery/module/i2c/__init__.py
robophery/module/i2c/am2320.py
robophery/module/i2c/bh1750.py
robophery/module/i2c/bme280.py
robophery/module/i2c/bmp085.py
robophery/module/i2c/ezoec.py
robophery/module/i2c/ezoph.py
robophery/module/i2c/htu21d.py
robophery/module/i2c/ina219.py
robophery/module/i2c/lsm9ds0.py
robophery/module/i2c/mcp9808.py
robophery/module/i2c/mpu6050.py
robophery/module/i2c/sht3x.py
robophery/module/i2c/si7021.py
robophery/module/i2c/ssd1306.py
robophery/module/i2c/t6713.py
robophery/module/i2c/tcs34725.py
robophery/module/i2c/tsl2561.py
robophery/module/i2c/tsl2591.py
robophery/module/i2c/vl53l0x.py
robophery/module/pwm/__init__.py
robophery/module/pwm/l293d.py
robophery/module/pwm/mod_switch.py
robophery/module/pwm/servo.py
robophery/module/virtual/__init__.py
robophery/module/virtual/gimball.py
robophery/module/virtual/tank.py
robophery/module/virtual/vr204.py
robophery/module/virtual/vr408.py
robophery/module/virtual/vr618.py
