Metadata-Version: 1.1
Name: robophery
Version: 0.2
Summary: Python library for interfacing low level hardware sensors and actuators with MQTT bindings.
Home-page: http://www.github.cz/cznewt/robophery
Author: Aleš Komárek
Author-email: ales.komarek@newt.cz
License: Apache Software License
Platform: UNKNOWN
Classifier: Intended Audience :: System Administrators
Classifier: License :: OSI Approved :: Apache Software License
Classifier: Operating System :: POSIX :: Linux
Classifier: Programming Language :: Python
